fdndatapuller/__init__.py
fdndatapuller/halcyon.py
fdndatapuller/tests/__init__.py
fdndatapuller/tests/cleaner_test.py
fdndatapuller/util/__init__.py
fdndatapuller/util/bot.py
fdndatapuller/util/cleaner.py
fdndatapuller/util/config.py
fdndatapuller/util/cypher.py
fdndatapuller/util/dateutil.py
fdndatapuller/util/db.py
fdndatapuller/util/input.py
fdndatapuller/util/log.py
fdndatapuller/util/netloc.py
fdndatapuller/util/whoami.py
fdndatapuller-1.0.2.data/scripts/halcyon
halcyon/__init__.py
tests/__init__.py
tests/cleaner_test.py
util/__init__.py
util/bot.py
util/cleaner.py
util/config.py
util/cypher.py
util/dateutil.py
util/db.py
util/input.py
util/log.py
util/netloc.py
util/whoami.py
fdndatapuller-1.0.2.dist-info/LICENSE
fdndatapuller-1.0.2.dist-info/METADATA
fdndatapuller-1.0.2.dist-info/WHEEL
fdndatapuller-1.0.2.dist-info/top_level.txt
fdndatapuller-1.0.2.dist-info/RECORD
