Metadata-Version: 2.1
Name: fdndatapuller
Version: 1.0.2
Summary: Script Puller
Home-page: UNKNOWN
Author: Ykäz Mihar
Author-email: zaky@femaledaily.com
License: UNKNOWN
Platform: UNKNOWN
Classifier: Programming Language :: Python :: 3
Classifier: License :: OSI Approved :: MIT License
Classifier: Operating System :: OS Independent
